fava_investor/__init__.py
fava_investor/cli/__init__.py
fava_investor/cli/investor.py
fava_investor/common/__init__.py
fava_investor/common/beancountinvestorapi.py
fava_investor/common/clicommon.py
fava_investor/common/favainvestorapi.py
fava_investor/common/libinvestor.py
fava_investor/examples/beancount-example.config
fava_investor/examples/example.beancount
fava_investor/examples/huge-example.beancount
fava_investor/modules/__init__.py
fava_investor/modules/assetalloc_account/TODO.txt
fava_investor/modules/assetalloc_account/__init__.py
fava_investor/modules/assetalloc_account/assetalloc_account.py
fava_investor/modules/assetalloc_account/libaaacc.py
fava_investor/modules/assetalloc_class/README.md
fava_investor/modules/assetalloc_class/__init__.py
fava_investor/modules/assetalloc_class/assetalloc_class.py
fava_investor/modules/assetalloc_class/example.beancount
fava_investor/modules/assetalloc_class/libassetalloc.py
fava_investor/modules/assetalloc_class/multicurrency.beancount
fava_investor/modules/assetalloc_class/test_asset_allocation.py
fava_investor/modules/cashdrag/README.md
fava_investor/modules/cashdrag/__init__.py
fava_investor/modules/cashdrag/cashdrag.py
fava_investor/modules/cashdrag/design.md
fava_investor/modules/cashdrag/libcashdrag.py
fava_investor/modules/minimizegains/README.md
fava_investor/modules/minimizegains/TODO.md
fava_investor/modules/minimizegains/__init__.py
fava_investor/modules/minimizegains/example.beancount
fava_investor/modules/minimizegains/libminimizegains.py
fava_investor/modules/minimizegains/minimizegains.py
fava_investor/modules/minimizegains/test_minimizegains.py
fava_investor/modules/summarizer/README.md
fava_investor/modules/summarizer/__init__.py
fava_investor/modules/summarizer/design.md
fava_investor/modules/summarizer/example.beancount
fava_investor/modules/summarizer/libsummarizer.py
fava_investor/modules/summarizer/summarizer.py
fava_investor/modules/tlh/README.md
fava_investor/modules/tlh/TODO.txt
fava_investor-1.0.1.dist-info/LICENSE.md
fava_investor-1.0.1.dist-info/METADATA
fava_investor-1.0.1.dist-info/WHEEL
fava_investor-1.0.1.dist-info/entry_points.txt
fava_investor-1.0.1.dist-info/top_level.txt
fava_investor-1.0.1.dist-info/RECORD
