Metadata-Version: 2.2
Name: fava_investor
Version: 1.0.1
Summary: Fava extension and beancount libraries for investing
Home-page: https://github.com/redstreet/fava_investor
Author: Red S
Author-email: redstreet@users.noreply.github.com
License: GPL-3.0
Keywords: fava beancount accounting investment
Classifier: Development Status :: 4 - Beta
Classifier: Intended Audience :: Financial and Insurance Industry
Classifier: License :: OSI Approved :: GNU General Public License v3 (GPLv3)
Classifier: Natural Language :: English
Classifier: Programming Language :: Python :: 3 :: Only
Classifier: Programming Language :: Python :: 3.8
Classifier: Topic :: Internet :: WWW/HTTP :: Dynamic Content
Classifier: Topic :: Office/Business :: Financial :: Accounting
Classifier: Topic :: Office/Business :: Financial :: Investment
License-File: LICENSE.md
Requires-Dist: Click>=7.0
Requires-Dist: beancount>=2.3.2
Requires-Dist: click_aliases>=1.0.1
Requires-Dist: fava>=1.26
Requires-Dist: packaging>=20.3
Requires-Dist: python_dateutil>=2.8.1
Requires-Dist: tabulate>=0.8.9
Requires-Dist: yfinance>=0.1.70
Dynamic: author
Dynamic: author-email
Dynamic: classifier
Dynamic: description
Dynamic: description-content-type
Dynamic: home-page
Dynamic: keywords
Dynamic: license
Dynamic: requires-dist
Dynamic: summary
